macroeconomy/__init__.py
macroeconomy/tool.py
macroeconomy-0.1.0.dist-info/licenses/LICENSE.txt
macroeconomy-0.1.0.dist-info/METADATA
macroeconomy-0.1.0.dist-info/WHEEL
macroeconomy-0.1.0.dist-info/entry_points.txt
macroeconomy-0.1.0.dist-info/top_level.txt
macroeconomy-0.1.0.dist-info/RECORD
